{
	"Андорра": "Андорра",
	"Об'єднані Арабські Емірати": "Об'єднані Арабські Емірати",
	"Афганістан": "Афганістан",
	"Антигуа і Барбуда": "Антигуа і Барбуда",
	"Албанія": "Албанія",
	"Арменія": "Арменія",
	"Ангола": "Ангола",
	"Аргентина": "Аргентина",
	"Австрія": "Австрія",
	"Азербайджан": "Азербайджан",
	"Боснія і Герцеговина": "Боснія і Герцеговина",
	"Барбадос": "Барбадос",
	"Бангладеш": "Бангладеш",
	"Бельгія": "Бельгія",
	"Буркина-Фасо": "Буркина-Фасо",
	"Болгарія": "Болгарія",
	"Бахрейн": "Бахрейн",
	"Бурунди": "Бурунди",
	"Бенин": "Бенин",
	"Сен-Бартельми": "Сен-Бартелемі",
	"Бруней-Даруссалам": "Бруней-Даруссалам",
	"Болівія": "Болівія",
	"Бразилія": "Бразилія",
	"Багамські острови": "Багамські острови",
	"Бутан": "Бутан",
	"Ботсвана": "Ботсвана",
	"Білорусь": "Білорусь",
	"Беліз": "Беліз",
	"Канада": "Канада",
	"Демократична Республіка Конго": "Демократична Республіка Конго",
	"Центральноафриканская Республіка": "Центральноафриканская Республіка",
	"Конго": "Конго",
	"Швейцарія": "Швейцарія",
	"Кот-д'Івуар": "Кот-д'Ивуар",
	"Чилі": "Чилі",
	"Камерун": "Камерун",
	"Китай": "Китай",
	"Колумбія": "Колумбія",
	"Коста-Рика": "Коста-Рика",
	"Куба": "Куба",
	"Кабо-Верде": "Кабо-Верде",
	"Кипр": "Кипр",
	"Чеська республіка": "Чеська республіка",
	"Німеччина": "Німеччина",
	"Джибути": "Джибути",
	"Данія": "Данія",
	"Домініка": "Домініка",
	"Домініканська Республіка": "Домініканська Республіка",
	"Алжир": "Алжир",
	"Эквадор": "Эквадор",
	"Эстония": "Эстония",
	"Егіпет": "Єгипет",
	"Эритрея": "Эритрея",
	"Іспанія": "Іспанія",
	"Эфиопия": "Эфиопия",
	"Фінляндія": "Фінляндія",
	"Фіджи": "Фіджі",
	"Федеративні штати Мікронезії": "Федеративні штати Мікронезії",
	"Франція": "Франція",
	"Габон": "Габон",
	"Великобританія": "Великобританія",
	"Гренада": "Гренада",
	"Грузія": "Грузія",
	"Гернси": "Гернси",
	"Гана": "Гана",
	"Гамбія": "Гамбія",
	"Гвінея": "Гвінея",
	"Экваториальная Гвинея": "Экваториальная Гвинея",
	"Греція": "Греція",
	"Гватемала": "Гватемала",
	"Гвінея-Бісау": "Гвінея-Бісау",
	"Гайана": "Гайана",
	"Гондурас": "Гондурас",
	"Хорватия": "Хорватия",
	"Гаїти": "Гаїти",
	"Венгрія": "Венгрія",
	"Індонезія": "Індонезія",
	"Ірландия": "Ірландия",
	"Израиль": "Израиль",
	"Остров Мэн": "Остров Мэн",
	"Індія": "Індія",
	"Ірак": "Ірак",
	"Іран": "Іран",
	"Ісландія": "Ісландія",
	"Італія": "Італія",
	"Джерси": "Джерси",
	"Ямайка": "Ямайка",
	"Джордан": "Джордан",
	"Японія": "Японія",
	"Кенія": "Кенія",
	"Кыргызстан": "Кыргызстан",
	"Камбоджа": "Камбоджа",
	"Кирибати": "Кирибати",
	"Сент-Кітс і Невіс": "Сент-Кітс і Невіс",
	"Коморрос": "Коморрос",
	"Северна Корея": "Северна Корея",
	"Южна Корея": "Южна Корея",
	"Кувейт": "Кувейт",
	"Казахстан": "Казахстан",
	"Лаос": "Лаос",
	"Ліхтенштейн": "Ліхтенштейн",
	"Ліван": "Ливан",
	"Шрі-Ланка": "Шрі-Ланка",
	"Либерия": "Либерия",
	"Лесото": "Лесото",
	"Литва": "Литва",
	"Люксембург": "Люксембург",
	"Латвія": "Латвія",
	"Лівія": "Лівія",
	"Марокко": "Марокко",
	"Молдова": "Молдова",
	"Черногория": "Черногория",
	"Сен-Мартен (французька частина)": "Сен-Мартен (французька частина)",
	"Мадагаскар": "Мадагаскар",
	"Маршаллові Острова": "Маршаллови Острова",
	"Македонія": "Македонія",
	"Малі": "Малі",
	"Мьянма": "Мьянма",
	"Монголия": "Монголия",
	"Макао": "Макао",
	"Мавританія": "Мавританія",
	"Мальта": "Мальта",
	"Маврикий": "Маврикий",
	"Мальдиви": "Мальдиви",
	"Малави": "Малави",
	"Мексика": "Мексика",
	"Малайзія": "Малайзія",
	"Мозамбик": "Мозамбик",
	"Намібія": "Намібія",
	"Нігер": "Нігер",
	"Нігерія": "Нігерія",
	"Никарагуа": "Никарагуа",
	"Нідерланди": "Нідерланди",
	"Норвегія": "Норвегія",
	"Непал": "Непал",
	"Науру": "Науру",
	"Нова Зеландія": "Нова Зеландія",
	"Оман": "Оман",
	"Панама": "Панама",
	"Перу": "Перу",
	"Папуа-Нова Гвінея": "Папуа-Нова Гвінея",
	"Філіппіни": "Філіппіни",
	"Пакистан": "Пакистан",
	"Польша": "Польша",
	"Палестинська територія, окупірована": "Палестинська територія, окупірована",
	"Португалія": "Португалія",
	"Палау": "Палау",
	"Парагвай": "Парагвай",
	"Катар": "Катар",
	"Румыния": "Румыния",
	"Сербія": "Сербія",
	"Россия": "Росія",
	"Руанда": "Руанда",
	"Саудовская Аравія": "Саудовская Аравия",
	"Соломонові острови": "Соломонові острови",
	"Сейшельські Острови": "Сейшельські Острови",
	"Судан": "Судан",
	"Швеція": "Швеція",
	"Сингапур": "Сингапур",
	"Святой Елены": "Святой Елены",
	"Словенія": "Словенія",
	"Словаччина": "Словаччина",
	"Сьерра-Леоне": "Сьерра-Леоне",
	"Сан-Марино": "Сан-Марино",
	"Сенегал": "Сенегал",
	"Сомалі": "Сомалі",
	"Суринам": "Суринам",
	"Сан-Томе і Принсипі": "Сан-Томе і Принсипі",
	"Сальвадор": "Сальвадор",
	"Сирія": "Сирія",
	"Свазиленд": "Свазиленд",
	"Чад": "Чад",
	"Того": "Того",
	"Таїланд": "Таїланд",
	"Таджикистан": "Таджикистан",
	"Восточный Тимор": "Восточный Тимор",
	"Туркменистан": "Туркменистан",
	"Туніс": "Туніс",
	"Тонга": "Тонга",
	"Турция": "Турция",
	"Тринідад і Тобаго": "Тринідад і Тобаго",
	"Тувалу": "Тувалу",
	"Тайвань": "Тайвань",
	"Танзанія": "Танзанія",
	"Україна": "Україна",
	"Уганда": "Уганда",
	"Малі віддалені острови США": "Малі віддалені острови США",
	"Соединенные штаты": "Соединенные штаты",
	"Уругвай": "Уругвай",
	"Узбекистан": "Узбекистан",
	"Сент-Винсент і Гренадини": "Сент-Винсент і Гренадини",
	"Венесуэла": "Венесуэла",
	"Вьетнам": "Вьетнам",
	"Вануату": "Вануату",
	"Самоа": "Самоа",
	"Йемен": "Йемен",
	"Южна Африка": "Южна Африка",
	"Замбія": "Замбія",
	"Зимбабве": "Зімбабве"
}
